mailtrigger/__init__.py
mailtrigger/argument.py
mailtrigger/banner.py
mailtrigger/main.py
mailtrigger/registry.py
mailtrigger/version.py
mailtrigger/auther/__init__.py
mailtrigger/auther/auther.py
mailtrigger/config/auther.json
mailtrigger/config/mailer.json
mailtrigger/config/scheduler.json
mailtrigger/config/trigger.json
mailtrigger/logger/__init__.py
mailtrigger/logger/logger.py
mailtrigger/mailer/__init__.py
mailtrigger/mailer/receiver.py
mailtrigger/mailer/sender.py
mailtrigger/scheduler/__init__.py
mailtrigger/scheduler/scheduler.py
mailtrigger/trigger/__init__.py
mailtrigger/trigger/gerrit.py
mailtrigger/trigger/helper.py
mailtrigger/trigger/jenkins.py
mailtrigger/trigger/jira.py
mailtrigger/trigger/printer.py
mailtrigger/trigger/trigger.py
mailtrigger-4.0.0.dist-info/LICENSE
mailtrigger-4.0.0.dist-info/METADATA
mailtrigger-4.0.0.dist-info/WHEEL
mailtrigger-4.0.0.dist-info/entry_points.txt
mailtrigger-4.0.0.dist-info/top_level.txt
mailtrigger-4.0.0.dist-info/RECORD
