Metadata-Version: 2.1
Name: mailtrigger
Version: 4.0.0
Summary: Remote service trigger with mail
Home-page: https://github.com/craftslab/mailtrigger
Author: Jia Jia
Author-email: angersax@sina.com
License: Apache-2.0
Download-URL: https://github.com/craftslab/mailtrigger/archive/v4.0.0.tar.gz
Keywords: gerrit,jenkins,mail,mailtrigger,trigger
Platform: UNKNOWN
Classifier: Programming Language :: Python :: 3
Classifier: License :: OSI Approved :: Apache Software License
Classifier: Operating System :: OS Independent
Requires-Dist: colorama
Requires-Dist: coverage
Requires-Dist: coveralls
Requires-Dist: html2text
Requires-Dist: openpyxl
Requires-Dist: paramiko
Requires-Dist: pytest
Requires-Dist: schedule
Requires-Dist: setuptools
Requires-Dist: twine
Requires-Dist: wheel
